ffmpeg_screenshot_pipe/README.md
ffmpeg_screenshot_pipe/__init__.py
ffmpeg_screenshot_pipe/ffmpeg.exe
ffmpeg_screenshot_pipe/ffmpeg_screenshot_pipe_multi.py
ffmpeg_screenshot_pipe/requirements.txt
ffmpeg_screenshot_pipe/thirdparty.json
ffmpeg_screenshot_pipe-0.10.dist-info/LICENSE.rst
ffmpeg_screenshot_pipe-0.10.dist-info/METADATA
ffmpeg_screenshot_pipe-0.10.dist-info/WHEEL
ffmpeg_screenshot_pipe-0.10.dist-info/top_level.txt
ffmpeg_screenshot_pipe-0.10.dist-info/RECORD
