Metadata-Version: 2.1
Name: ffmpeg-screenshot-pipe
Version: 0.10
Summary: Capture Screenshots with Unparalleled Speed and Versatile Features - GDIgrab, DDAgrab, Ctypes, Multiprocessing, GPU, Mouse Capture...
Home-page: https://github.com/hansalemaos/ffmpeg_screenshot_pipe
Author: Johannes Fischer
Author-email: aulasparticularesdealemaosp@gmail.com
License: MIT
Keywords: screenshots,mss,fast,win32,ffmpeg,gdigrab,ddagrab
Classifier: Development Status :: 4 - Beta
Classifier: Programming Language :: Python :: 3 :: Only
Classifier: Programming Language :: Python :: 3.10
Classifier: Topic :: Software Development :: Libraries :: Python Modules
Classifier: Topic :: Utilities
License-File: LICENSE.rst
Requires-Dist: appshwnd
Requires-Dist: fast-ctypes-screenshots
Requires-Dist: fastimgconcat
Requires-Dist: get-rectangle-infos
Requires-Dist: getfilenuitkapython
Requires-Dist: getmonitorresolution
Requires-Dist: kthread
Requires-Dist: kthread-sleep
Requires-Dist: numpy
Requires-Dist: subprocess-alive
Requires-Dist: subprocesskiller
